sphinx_conestack_theme/__init__.py
sphinx_conestack_theme/conestack/external.html
sphinx_conestack_theme/conestack/footer.html
sphinx_conestack_theme/conestack/github.html
sphinx_conestack_theme/conestack/gitlab.html
sphinx_conestack_theme/conestack/layout.html
sphinx_conestack_theme/conestack/localtoc.html
sphinx_conestack_theme/conestack/logo.html
sphinx_conestack_theme/conestack/mobiletoc.html
sphinx_conestack_theme/conestack/navigationtoc.html
sphinx_conestack_theme/conestack/npm.html
sphinx_conestack_theme/conestack/pypi.html
sphinx_conestack_theme/conestack/relations.html
sphinx_conestack_theme/conestack/search.html
sphinx_conestack_theme/conestack/searchbox.html
sphinx_conestack_theme/conestack/sidebar.html
sphinx_conestack_theme/conestack/theme.conf
sphinx_conestack_theme/conestack/twitter.html
sphinx_conestack_theme/conestack/static/conestack.svg
sphinx_conestack_theme/conestack/static/bootstrap/bootstrap.bundle.min.js
sphinx_conestack_theme/conestack/static/bootstrap/bootstrap.bundle.min.js.map
sphinx_conestack_theme/conestack/static/bootstrap/bootstrap.css
sphinx_conestack_theme/conestack/static/bootstrap/bootstrap.css.map
sphinx_conestack_theme/conestack/static/bootstrap/bootstrap-icons/bootstrap-icons.css
sphinx_conestack_theme/conestack/static/bootstrap/bootstrap-icons/bootstrap-icons.json
sphinx_conestack_theme/conestack/static/bootstrap/bootstrap-icons/bootstrap-icons.svg
sphinx_conestack_theme/conestack/static/bootstrap/bootstrap-icons/fonts/bootstrap-icons.woff
sphinx_conestack_theme/conestack/static/bootstrap/bootstrap-icons/fonts/bootstrap-icons.woff2
sphinx_conestack_theme/conestack/static/css/conestack-vars.css
sphinx_conestack_theme/conestack/static/css/conestack.css
sphinx_conestack_theme/conestack/static/css/conestack.css.map
sphinx_conestack_theme/conestack/static/css/conestack.min.css
sphinx_conestack_theme/conestack/static/css/pygments.css
sphinx_conestack_theme/conestack/static/js/colortoggle.js
sphinx_conestack_theme-1.1.1.dist-info/METADATA
sphinx_conestack_theme-1.1.1.dist-info/WHEEL
sphinx_conestack_theme-1.1.1.dist-info/entry_points.txt
sphinx_conestack_theme-1.1.1.dist-info/licenses/LICENSE.rst
sphinx_conestack_theme-1.1.1.dist-info/RECORD
