Metadata-Version: 2.4
Name: sphinx-conestack-theme
Version: 1.1.1
Summary: Mobile friendly Bootstrap 5 based Sphinx theme
Project-URL: Homepage, https://conestack.github.io/sphinx-conestack-theme
Project-URL: Code, https://github.com/conestack/sphinx-conestack-theme
Author-email: Cone Contributors <dev@conestack.org>
License: BSD 2-Clause License
License-File: LICENSE.rst
Keywords: Sphinx,conestack,theme
Classifier: Environment :: Web Environment
Classifier: Intended Audience :: Developers
Classifier: Intended Audience :: System Administrators
Classifier: License :: OSI Approved :: BSD License
Classifier: Operating System :: OS Independent
Classifier: Programming Language :: Python
Classifier: Programming Language :: Python :: 3.10
Classifier: Programming Language :: Python :: 3.11
Classifier: Programming Language :: Python :: 3.12
Classifier: Programming Language :: Python :: 3.13
Classifier: Programming Language :: Python :: 3.14
Classifier: Topic :: Software Development
Classifier: Topic :: Software Development :: Documentation
Requires-Python: >=3.10
Requires-Dist: sphinx
